{
  "collectionName": "components_home_heroes",
  "info": {
    "displayName": "Layout 1",
    "icon": "quote-left",
    "description": ""
  },
  "options": {},
  "attributes": {
    "heading": {
      "type": "string"
    },
    "description": {
      "type": "text"
    },
    "heroImage": {
      "type": "media",
      "multiple": false,
      "required": false,
      "allowedTypes": [
        "images",
        "files",
        "videos",
        "audios"
      ]
    },
    "buttonText": {
      "type": "string"
    },
    "buttonUrl": {
      "type": "string"
    },
    "listItems": {
      "displayName": "listItems",
      "type": "component",
      "repeatable": true,
      "component": "home.list-items"
    },
    "videoUrl": {
      "type": "string"
    }
  }
}
